lpc_checksum.py
lpc_checksum-2.2.0.dist-info/LICENSE
lpc_checksum-2.2.0.dist-info/METADATA
lpc_checksum-2.2.0.dist-info/WHEEL
lpc_checksum-2.2.0.dist-info/entry_points.txt
lpc_checksum-2.2.0.dist-info/top_level.txt
lpc_checksum-2.2.0.dist-info/RECORD
