Metadata-Version: 2.1
Name: lpc_checksum
Version: 2.2.0
Summary: Python script to calculate LPC firmware checksums
Home-page: https://github.com/basilfx/lpc_checksum
Author: Bas Stottelaar
Author-email: basstottelaar@gmail.com
License: MIT
Keywords: lpc mcu cortex nxp flashing
Platform: any
Classifier: Development Status :: 5 - Production/Stable
Classifier: Intended Audience :: Developers
Classifier: License :: OSI Approved :: MIT License
Classifier: Topic :: Software Development :: Embedded Systems
Classifier: Programming Language :: Python :: 2
Classifier: Programming Language :: Python :: 2.7
Classifier: Programming Language :: Python :: 3
Classifier: Programming Language :: Python :: 3.5
Classifier: Programming Language :: Python :: 3.6
Classifier: Programming Language :: Python :: 3.7
Classifier: Programming Language :: Python :: 3.8
Provides-Extra: development
